fintix_modelcurator/__init__.py
fintix_modelcurator/callback.py
fintix_modelcurator/cbhandler.py
fintix_modelcurator/check_json.py
fintix_modelcurator/config.py
fintix_modelcurator/const.py
fintix_modelcurator/error.py
fintix_modelcurator/exit_code.py
fintix_modelcurator/modelhandler.py
fintix_modelcurator/phase.py
fintix_modelcurator/repository.py
fintix_modelcurator/settings.py
fintix_modelcurator/trigger_type.py
fintix_modelcurator/utils.py
fintix_modelcurator-0.1.25.dist-info/WHEEL
fintix_modelcurator-0.1.25.dist-info/METADATA
fintix_modelcurator-0.1.25.dist-info/RECORD
